pynalytics/.DS_Store
pynalytics/data_pipeline/__init__.py
pynalytics/data_pipeline/feature_engineering/__init__.py
pynalytics/data_pipeline/feature_engineering/key_smash.py
pynalytics/data_pipeline/feature_engineering/word_embedding.py
pynalytics/data_pipeline/pre_processing/__init__.py
pynalytics/data_pipeline/pre_processing/concatenate_columns.py
pynalytics/main.py
pynalytics/parser/YAML_parser.py
pynalytics/parser/__init__.py
pynalytics/parser/const.py
pynalytics/parser/feature_engineering_parser.py
pynalytics/parser/model_parser.py
pynalytics/parser/parser_base.py
pynalytics/yamls/basic_example.yaml
pynalytics-1.1.1.dist-info/METADATA
pynalytics-1.1.1.dist-info/entry_points.txt
pynalytics-1.1.1.dist-info/WHEEL
pynalytics-1.1.1.dist-info/LICENSE
pynalytics-1.1.1.dist-info/RECORD
