Metadata-Version: 2.1
Name: pynalytics
Version: 1.1.1
Summary: This is a lib from developed for the individual work related to the Software Evolution and Configuration Management subject from UnB - Universidade de Brasília during the 2022.2 semester
Home-page: https://github.com/JPedroCh/Trabalho-Individual-2022-2
License: MIT
Keywords: metabase,parser,data
Author: João Pedro Chaves
Author-email: joaopedroaschaves@gmail.com
Requires-Python: ==3.9.16
Classifier: License :: OSI Approved :: MIT License
Classifier: Programming Language :: Python :: 3
Requires-Dist: Jinja2 (==3.1.2)
Requires-Dist: MarkupSafe (==2.1.1)
Requires-Dist: Pillow (==9.4.0)
Requires-Dist: PyYAML (==6.0)
Requires-Dist: altair (==4.2.0)
Requires-Dist: attrs (==22.2.0)
Requires-Dist: bpemb (==0.3.4)
Requires-Dist: certifi (==2022.12.7)
Requires-Dist: charset-normalizer (==2.1.1)
Requires-Dist: contourpy (==1.0.6)
Requires-Dist: coverage (==7.0.2)
Requires-Dist: cycler (==0.11.0)
Requires-Dist: entrypoints (==0.4)
Requires-Dist: exceptiongroup (==1.1.0)
Requires-Dist: fonttools (==4.38.0)
Requires-Dist: gensim (==3.8.3)
Requires-Dist: idna (==3.4)
Requires-Dist: importlib-resources (==5.10.2)
Requires-Dist: iniconfig (==1.1.1)
Requires-Dist: joblib (==1.2.0)
Requires-Dist: jsonschema (==4.17.3)
Requires-Dist: kiwisolver (==1.4.4)
Requires-Dist: matplotlib (==3.6.2)
Requires-Dist: numpy (==1.24.1)
Requires-Dist: packaging (==22.0)
Requires-Dist: pandas (==1.5.2)
Requires-Dist: pkgutil-resolve-name (==1.3.10)
Requires-Dist: pluggy (==1.0.0)
Requires-Dist: pyparsing (==3.0.9)
Requires-Dist: pyrsistent (==0.19.3)
Requires-Dist: pytest (==7.2.0)
Requires-Dist: pytest-cov (==4.0.0)
Requires-Dist: python-dateutil (==2.8.2)
Requires-Dist: pytz (==2022.7)
Requires-Dist: requests (==2.28.1)
Requires-Dist: scikit-learn (==1.2.0)
Requires-Dist: scipy (==1.9.3)
Requires-Dist: sentencepiece (==0.1.97)
Requires-Dist: six (==1.16.0)
Requires-Dist: smart-open (==6.3.0)
Requires-Dist: threadpoolctl (==3.1.0)
Requires-Dist: tomli (==2.0.1)
Requires-Dist: toolz (==0.12.0)
Requires-Dist: tqdm (==4.64.1)
Requires-Dist: urllib3 (==1.26.13)
Requires-Dist: whatlies (==0.7.0)
Requires-Dist: zipp (==3.11.0)
Project-URL: Repository, https://github.com/JPedroCh/Trabalho-Individual-2022-2
